bosa_core.cpython-311-x86_64-linux-gnu.so
bosa_core.pyi
bosa_core/__init__.pyi
bosa_core/authentication/__init__.pyi
bosa_core/authentication/config.pyi
bosa_core/authentication/constants.pyi
bosa_core/authentication/database.pyi
bosa_core/authentication/provider.pyi
bosa_core/authentication/service.pyi
bosa_core/authentication/client/__init__.pyi
bosa_core/authentication/client/helper/__init__.pyi
bosa_core/authentication/client/helper/helper.pyi
bosa_core/authentication/client/repository/__init__.pyi
bosa_core/authentication/client/repository/base_repository.pyi
bosa_core/authentication/client/repository/models.pyi
bosa_core/authentication/client/repository/sqlalchemy/__init__.pyi
bosa_core/authentication/client/repository/sqlalchemy/models.pyi
bosa_core/authentication/client/repository/sqlalchemy/repository.pyi
bosa_core/authentication/client/service/__init__.pyi
bosa_core/authentication/client/service/client_aware_service.pyi
bosa_core/authentication/client/service/create_client_service.pyi
bosa_core/authentication/client/service/verify_client_service.pyi
bosa_core/authentication/common/__init__.pyi
bosa_core/authentication/common/base64_helper.pyi
bosa_core/authentication/database_migration/__init__.pyi
bosa_core/authentication/database_migration/base_migration.pyi
bosa_core/authentication/database_migration/migration.pyi
bosa_core/authentication/database_migration/migration_versions/V1_init_table_auth.pyi
bosa_core/authentication/database_migration/migration_versions/V2_multi_account_integration.pyi
bosa_core/authentication/database_migration/migration_versions/V3_add_integration_indexes.pyi
bosa_core/authentication/database_migration/migration_versions/V4_encrypt_auth_strings.pyi
bosa_core/authentication/database_migration/migration_versions/V5_add_field_clients_can_get_integrations.pyi
bosa_core/authentication/database_migration/migration_versions/V6_add_field_token_expire.pyi
bosa_core/authentication/database_migration/migration_versions/__init__.pyi
bosa_core_binary-0.9.7.dist-info/METADATA
bosa_core_binary-0.9.7.dist-info/WHEEL
bosa_core_binary-0.9.7.dist-info/top_level.txt
bosa_core_binary-0.9.7.dist-info/RECORD
