Metadata-Version: 2.2
Name: bosa-core-binary
Version: 0.9.7
Summary: BOSA Core Library
Author-email: Samuel Lusandi <samuel.lusandi@gdplabs.id>
Requires-Python: <3.14,>=3.11
Requires-Dist: passlib<2.0.0,>=1.7.4
Requires-Dist: pydantic-settings<3.0.0,>=2.7.1
Requires-Dist: pydantic<3.0.0,>=2.9.2
Provides-Extra: cache
Requires-Dist: redis<6.0.0,>=5.2.1; extra == "cache"
Provides-Extra: telemetry
Requires-Dist: fastapi<1.0.0,>=0.115.6; extra == "telemetry"
Requires-Dist: requests<3.0.0,>=2.31.0; extra == "telemetry"
Requires-Dist: httpx<1.0.0,>=0.27.0; extra == "telemetry"
Requires-Dist: langchain-core<1.0.0,>=0.3; extra == "telemetry"
Requires-Dist: sentry-sdk<3.0.0,>=2.20.0; extra == "telemetry"
Requires-Dist: opentelemetry-api; extra == "telemetry"
Requires-Dist: opentelemetry-sdk; extra == "telemetry"
Requires-Dist: opentelemetry-exporter-otlp-proto-http; extra == "telemetry"
Requires-Dist: opentelemetry-exporter-otlp-proto-grpc; extra == "telemetry"
Requires-Dist: opentelemetry-instrumentation-fastapi; extra == "telemetry"
Requires-Dist: opentelemetry-instrumentation-langchain; extra == "telemetry"
Requires-Dist: opentelemetry-instrumentation-requests; extra == "telemetry"
Requires-Dist: opentelemetry-instrumentation-httpx; extra == "telemetry"
Provides-Extra: logger
Requires-Dist: requests<3.0.0,>=2.31.0; extra == "logger"
Provides-Extra: authentication
Requires-Dist: sqlalchemy<3.0.0,>=2.0.38; extra == "authentication"
Requires-Dist: alembic<2.0.0,>=1.15.1; extra == "authentication"
Requires-Dist: argon2-cffi<24.0.0,>=23.1.0; extra == "authentication"
Requires-Dist: joserfc<2.0.0,>=1.4.0; extra == "authentication"
Requires-Dist: psycopg2-binary<3.0.0,>=2.9.10; extra == "authentication"
Requires-Dist: cryptography<46.0.0,>=43.0.0; extra == "authentication"
Requires-Dist: redis<6.0.0,>=5.2.1; extra == "authentication"
Provides-Extra: plugin
Requires-Dist: python-dotenv<2.0.0,>=1.0.0; extra == "plugin"
Provides-Extra: all
Requires-Dist: redis<6.0.0,>=5.2.1; extra == "all"
Requires-Dist: fastapi<1.0.0,>=0.115.6; extra == "all"
Requires-Dist: requests<3.0.0,>=2.31.0; extra == "all"
Requires-Dist: httpx<1.0.0,>=0.28.1; extra == "all"
Requires-Dist: langchain-core<1.0.0,>=0.3; extra == "all"
Requires-Dist: sentry-sdk<3.0.0,>=2.20.0; extra == "all"
Requires-Dist: opentelemetry-api; extra == "all"
Requires-Dist: opentelemetry-sdk; extra == "all"
Requires-Dist: opentelemetry-exporter-otlp-proto-http; extra == "all"
Requires-Dist: opentelemetry-exporter-otlp-proto-grpc; extra == "all"
Requires-Dist: opentelemetry-instrumentation-fastapi; extra == "all"
Requires-Dist: opentelemetry-instrumentation-langchain; extra == "all"
Requires-Dist: opentelemetry-instrumentation-requests; extra == "all"
Requires-Dist: opentelemetry-instrumentation-httpx; extra == "all"
Requires-Dist: sqlalchemy<3.0.0,>=2.0.38; extra == "all"
Requires-Dist: alembic<2.0.0,>=1.15.1; extra == "all"
Requires-Dist: argon2-cffi<24.0.0,>=23.1.0; extra == "all"
Requires-Dist: joserfc<2.0.0,>=1.4.0; extra == "all"
Requires-Dist: psycopg2-binary<3.0.0,>=2.9.10; extra == "all"
Requires-Dist: cryptography<46.0.0,>=43.0.0; extra == "all"
Requires-Dist: python-dotenv<2.0.0,>=1.0.0; extra == "all"
Provides-Extra: dev
Requires-Dist: pre-commit<4.0.0,>=3.6.2; extra == "dev"
Requires-Dist: pytest<9.0.0,>=8.3.4; extra == "dev"
Requires-Dist: pytest-mock<4.0.0,>=3.14.0; extra == "dev"
Requires-Dist: pytest-asyncio<1.0.0,>=0.25.3; extra == "dev"
Requires-Dist: coverage<8.0.0,>=7.6.10; extra == "dev"
Requires-Dist: mypy<2.0.0,>=1.11.2; extra == "dev"
Requires-Dist: ruff<1.0.0,>=0.9.9; extra == "dev"
Requires-Dist: pytest-cov<6.0.0,>=5.0.0; extra == "dev"
